{
    "algorithm_desc": "pymoo_NSGA3_algorithm",
    "scenario_name": "6vessel_0obstacle",
    "random_seed": 1234,
    "vessel_number": 6,
    "obstacle_number": 0,
    "evaluation_time": 179.967043,
    "number_of_generations": 1280,
    "population_size": 20.0,
    "num_parents_mating": 2,
    "best_fitness": [
        0.00876622044861474,
        0.008688390168728433,
        8.169804519528754e-05,
        0.0,
        0.0,
        3.867765308979478e-06
    ],
    "mutate_eta": 15.0,
    "mutate_prob": 1.0,
    "crossover_eta": 10.0,
    "crossover_prob": 0.2,
    "error_message": null,
    "timestamp": "2025-04-09T21:37:05.485962",
    "measurement_name": "parameter_optimization_2",
    "path": "/home/ubuntu/Desktop/USVLogicSceneGeneration/src/utils/../../assets/gen_data/parameter_optimization_2/SB-MSR/pymoo_NSGA3_algorithm_actor/6vessel_0obstacle_2025-04-09T21-37-05.485962.json",
    "timeout": 180,
    "init_method": "uniform",
    "c_1": null,
    "c_2": null,
    "w": null,
    "best_fitness_index": 0.00877008821392372,
    "aggregate_strat": "actor",
    "config_group": "SB-MSR",
    "best_scene": {
        "_data": [
            [
                {
                    "id": 0,
                    "radius": 120.00000000000534,
                    "type": "OSPassengerShip",
                    "is_os": true,
                    "length": 30.000000000001336,
                    "max_speed": 20.577787999999998,
                    "beam": null,
                    "is_vessel": true
                },
                {
                    "x": 12038.0064999999,
                    "y": 12038.006500000014,
                    "speed": 14.56953384829682,
                    "heading": 1.5707963268791272
                }
            ],
            [
                {
                    "id": 1,
                    "radius": 1259.745056280598,
                    "type": "OtherType",
                    "is_os": false,
                    "length": 314.9362640701495,
                    "max_speed": 25.722234999999998,
                    "beam": null,
                    "is_vessel": true
                },
                {
                    "x": 8361.618504627584,
                    "y": 20248.455026776104,
                    "speed": 7.63431676298675,
                    "heading": 0.8136256034265272
                }
            ],
            [
                {
                    "id": 2,
                    "radius": 383.65342220910287,
                    "type": "OtherType",
                    "is_os": false,
                    "length": 95.91335555227572,
                    "max_speed": 25.722234999999998,
                    "beam": null,
                    "is_vessel": true
                },
                {
                    "x": 11782.233419561695,
                    "y": 17640.387659261538,
                    "speed": 0.9070325049789423,
                    "heading": 1.7505879435798624
                }
            ],
            [
                {
                    "id": 3,
                    "radius": 491.0349337664215,
                    "type": "OtherType",
                    "is_os": false,
                    "length": 122.75873344160537,
                    "max_speed": 25.722234999999998,
                    "beam": null,
                    "is_vessel": true
                },
                {
                    "x": 14643.16816911849,
                    "y": 16925.489201570457,
                    "speed": 9.009649449192297,
                    "heading": 1.993288730290733
                }
            ],
            [
                {
                    "id": 4,
                    "radius": 1590.1038303253777,
                    "type": "OtherType",
                    "is_os": false,
                    "length": 397.5259575813444,
                    "max_speed": 25.722234999999998,
                    "beam": null,
                    "is_vessel": true
                },
                {
                    "x": 13119.440968208322,
                    "y": 8519.118347905483,
                    "speed": 25.455187291762932,
                    "heading": 1.7453416625935625
                }
            ],
            [
                {
                    "id": 5,
                    "radius": 1080.6667174012168,
                    "type": "OtherType",
                    "is_os": false,
                    "length": 270.1666793503042,
                    "max_speed": 25.722234999999998,
                    "beam": null,
                    "is_vessel": true
                },
                {
                    "x": 11884.444708823496,
                    "y": 17641.392788199482,
                    "speed": 2.394937056905613,
                    "heading": 2.7682926964374683
                }
            ]
        ],
        "dcpa": null,
        "tcpa": null,
        "danger_sector": null,
        "proximity_index": null
    }
}