{
    "algorithm_desc": "pymoo_NSGA3_algorithm",
    "scenario_name": "6vessel_0obstacle",
    "random_seed": 1234,
    "vessel_number": 6,
    "obstacle_number": 0,
    "evaluation_time": 9.877554,
    "number_of_generations": 381,
    "population_size": 6,
    "num_parents_mating": 2,
    "best_fitness": [
        0.0,
        0.0,
        0.0,
        0.0,
        0.0,
        0.0
    ],
    "mutate_eta": 10.0,
    "mutate_prob": 0.2,
    "crossover_eta": 20.0,
    "crossover_prob": 0.2,
    "error_message": null,
    "timestamp": "2025-05-03T20:27:48.090606",
    "measurement_name": "parameter_optimization_2",
    "path": "/home/ubuntu/Desktop/USVLogicSceneGeneration/src/utils/../../assets/gen_data/parameter_optimization_2/SB-O/pymoo_NSGA3_algorithm_actor/6vessel_0obstacle_2025-05-03T20-27-48.090606.json",
    "timeout": 180,
    "init_method": "uniform",
    "c_1": null,
    "c_2": null,
    "w": null,
    "best_fitness_index": 0.0,
    "aggregate_strat": "actor",
    "config_group": "SB-O",
    "best_scene": {
        "_data": [
            [
                {
                    "id": 0,
                    "radius": 120.00000000006288,
                    "type": "OSPassengerShip",
                    "is_os": true,
                    "length": 30.00000000001572,
                    "max_speed": 20.577787999999998,
                    "beam": null,
                    "is_vessel": true
                },
                {
                    "x": 12038.006499999961,
                    "y": 12038.0064999999,
                    "speed": 19.364789865745223,
                    "heading": 1.5707963266970297
                }
            ],
            [
                {
                    "id": 1,
                    "radius": 1449.5677095812036,
                    "type": "OtherType",
                    "is_os": false,
                    "length": 362.3919273953009,
                    "max_speed": 25.722234999999998,
                    "beam": null,
                    "is_vessel": true
                },
                {
                    "x": 11617.365985995184,
                    "y": 21262.255148833876,
                    "speed": 2.2730267873048144,
                    "heading": 0.34549593911902476
                }
            ],
            [
                {
                    "id": 2,
                    "radius": 942.8444747520957,
                    "type": "OtherType",
                    "is_os": false,
                    "length": 235.71111868802393,
                    "max_speed": 25.722234999999998,
                    "beam": null,
                    "is_vessel": true
                },
                {
                    "x": 8939.248281586111,
                    "y": 20785.304697012332,
                    "speed": 12.847755398362128,
                    "heading": -0.9428438208598122
                }
            ],
            [
                {
                    "id": 3,
                    "radius": 1583.920679614912,
                    "type": "OtherType",
                    "is_os": false,
                    "length": 395.980169903728,
                    "max_speed": 25.722234999999998,
                    "beam": null,
                    "is_vessel": true
                },
                {
                    "x": 4160.53725061001,
                    "y": 16926.32472341632,
                    "speed": 19.0647192683781,
                    "heading": 0.5516856176080152
                }
            ],
            [
                {
                    "id": 4,
                    "radius": 309.58469887797384,
                    "type": "OtherType",
                    "is_os": false,
                    "length": 77.39617471949346,
                    "max_speed": 25.722234999999998,
                    "beam": null,
                    "is_vessel": true
                },
                {
                    "x": 21335.129517890542,
                    "y": 12496.288585487528,
                    "speed": 20.84641152719368,
                    "heading": 2.0327034778878574
                }
            ],
            [
                {
                    "id": 5,
                    "radius": 1575.650159697005,
                    "type": "OtherType",
                    "is_os": false,
                    "length": 393.91253992425123,
                    "max_speed": 25.722234999999998,
                    "beam": null,
                    "is_vessel": true
                },
                {
                    "x": 19989.299116259786,
                    "y": 16870.359251896174,
                    "speed": 24.22989332573084,
                    "heading": 3.134575299788053
                }
            ]
        ],
        "dcpa": null,
        "tcpa": null,
        "danger_sector": null,
        "proximity_index": null,
        "first_level_hash": null,
        "second_level_hash": null,
        "is_relevant": null,
        "is_ambiguous": null
    }
}