<?xml version='1.0' encoding='UTF-8'?>
<commonOcean timeStepSize="10.0" commonOceanVersion="2022a" author="Hanna Krasowski, Bruno Maione" affiliation="Technical University of Munich, Germany" source="Marine Cadastre" benchmarkID="C-USA_FLO-1_2019011601" date="2022-08-02">
  <location>
    <geoNameId>1</geoNameId>
    <gpsLatitude>28.227529999999998</gpsLatitude>
    <gpsLongitude>-79.95425</gpsLongitude>
  </location>
  <scenarioTags>
    <open_sea/>
  </scenarioTags>
  <navigationableArea>
    <rectangle>
      <length>6639.02</length>
      <width>22085.37</width>
      <orientation>0.0</orientation>
      <center>
        <x>2336.17</x>
        <y>-10153.34</y>
      </center>
    </rectangle>
  </navigationableArea>
  <planningProblem id="367690001">
    <initialState>
      <position>
        <point>
          <x>0.0</x>
          <y>0.0</y>
        </point>
      </position>
      <orientation>
        <exact>4.8618042</exact>
      </orientation>
      <time>
        <exact>0</exact>
      </time>
      <velocity>
        <exact>10.64808</exact>
      </velocity>
    </initialState>
    <goalState>
      <position>
        <rectangle>
          <length>300.0</length>
          <width>40.0</width>
          <orientation>0.0</orientation>
          <center>
            <x>3039.2467</x>
            <y>-20196.028</y>
          </center>
        </rectangle>
      </position>
      <orientation>
        <intervalStart>4.7697156</intervalStart>
        <intervalEnd>4.9697156</intervalEnd>
      </orientation>
      <time>
        <intervalStart>188</intervalStart>
        <intervalEnd>208</intervalEnd>
      </time>
    </goalState>
  </planningProblem>
  <planningProblem id="367690002">
    <initialState>
      <position>
        <point>
          <x>4661.9316</x>
          <y>-18304.716</y>
        </point>
      </position>
      <orientation>
        <exact>1.6570335</exact>
      </orientation>
      <time>
        <exact>6</exact>
      </time>
      <velocity>
        <exact>6.89296</exact>
      </velocity>
    </initialState>
    <goalState>
      <position>
        <rectangle>
          <length>45.0</length>
          <width>14.0</width>
          <orientation>0.0</orientation>
          <center>
            <x>2001.5671</x>
            <y>-4650.4583</y>
          </center>
        </rectangle>
      </position>
      <orientation>
        <intervalStart>1.7803893</intervalStart>
        <intervalEnd>1.9803893</intervalEnd>
      </orientation>
      <time>
        <intervalStart>199</intervalStart>
        <intervalEnd>219</intervalEnd>
      </time>
    </goalState>
  </planningProblem>
</commonOcean>
