{
    "algorithm_desc": "pymoo_NSGA2_algorithm",
    "scenario_name": "6vessel_0obstacle",
    "random_seed": 1234,
    "vessel_number": 6,
    "obstacle_number": 0,
    "evaluation_time": 179.946814,
    "number_of_generations": 11248,
    "population_size": 2.0,
    "num_parents_mating": 2,
    "best_fitness": [
        0.47015754572596824,
        0.14264180342910526,
        0.011355000357278676,
        0.1318367031235118,
        0.05736841529098608,
        0.12695562352508644
    ],
    "mutate_eta": 5.0,
    "mutate_prob": 0.8,
    "crossover_eta": 10.0,
    "crossover_prob": 0.2,
    "error_message": null,
    "timestamp": "2025-04-10T08:38:05.113417",
    "measurement_name": "parameter_optimization_2",
    "path": "/home/ubuntu/Desktop/USVLogicSceneGeneration/src/utils/../../assets/gen_data/parameter_optimization_2/SB-MSR/pymoo_NSGA2_algorithm_actor/6vessel_0obstacle_2025-04-10T08-38-05.113417.json",
    "timeout": 180,
    "init_method": "uniform",
    "c_1": null,
    "c_2": null,
    "w": null,
    "best_fitness_index": 0.47015754572596824,
    "aggregate_strat": "actor",
    "config_group": "SB-MSR",
    "best_scene": {
        "_data": [
            [
                {
                    "id": 0,
                    "radius": 119.9999999997094,
                    "type": "OSPassengerShip",
                    "is_os": true,
                    "length": 29.99999999992735,
                    "max_speed": 20.577787999999998,
                    "beam": null,
                    "is_vessel": true
                },
                {
                    "x": 12038.006499999901,
                    "y": 12038.006500000014,
                    "speed": 15.34401686101804,
                    "heading": 1.5707963268672043
                }
            ],
            [
                {
                    "id": 1,
                    "radius": 1348.3805416496637,
                    "type": "OtherType",
                    "is_os": false,
                    "length": 337.0951354124159,
                    "max_speed": 25.722234999999998,
                    "beam": null,
                    "is_vessel": true
                },
                {
                    "x": 9918.632932399063,
                    "y": 12103.36912876267,
                    "speed": 11.419355710853969,
                    "heading": 2.242395452268724
                }
            ],
            [
                {
                    "id": 2,
                    "radius": 409.7769968718898,
                    "type": "OtherType",
                    "is_os": false,
                    "length": 102.44424921797246,
                    "max_speed": 25.722234999999998,
                    "beam": null,
                    "is_vessel": true
                },
                {
                    "x": 10252.806844715657,
                    "y": 16903.901588791417,
                    "speed": 9.863281598447,
                    "heading": 1.3365679778161468
                }
            ],
            [
                {
                    "id": 3,
                    "radius": 1317.6466689388353,
                    "type": "OtherType",
                    "is_os": false,
                    "length": 329.41166723470883,
                    "max_speed": 25.722234999999998,
                    "beam": null,
                    "is_vessel": true
                },
                {
                    "x": 14313.24621110813,
                    "y": 10741.99087194885,
                    "speed": 5.542350348299176,
                    "heading": -0.1621517425165273
                }
            ],
            [
                {
                    "id": 4,
                    "radius": 1593.9784313383423,
                    "type": "OtherType",
                    "is_os": false,
                    "length": 398.49460783458557,
                    "max_speed": 25.722234999999998,
                    "beam": null,
                    "is_vessel": true
                },
                {
                    "x": 11039.474554049646,
                    "y": 10262.49322498808,
                    "speed": 20.868266732411396,
                    "heading": 0.8745467672061427
                }
            ],
            [
                {
                    "id": 5,
                    "radius": 1599.0502803631239,
                    "type": "OtherType",
                    "is_os": false,
                    "length": 399.76257009078097,
                    "max_speed": 25.722234999999998,
                    "beam": null,
                    "is_vessel": true
                },
                {
                    "x": 8178.553888946497,
                    "y": 13074.340612994327,
                    "speed": 10.700662725888055,
                    "heading": -3.1162594789685962
                }
            ]
        ],
        "dcpa": null,
        "tcpa": null,
        "danger_sector": null,
        "proximity_index": null
    }
}