{
    "algorithm_desc": "pymoo_NSGA2_algorithm",
    "scenario_name": "6vessel_0obstacle",
    "random_seed": 1234,
    "vessel_number": 6,
    "obstacle_number": 0,
    "evaluation_time": 179.928521,
    "number_of_generations": 11500,
    "population_size": 2.0,
    "num_parents_mating": 2,
    "best_fitness": [
        0.14242873751516363,
        0.008339728974564892,
        0.07874402458495518,
        0.03672243938411337,
        0.0688899793103874,
        0.05026743473885722
    ],
    "mutate_eta": 20.0,
    "mutate_prob": 0.8,
    "crossover_eta": 1.0,
    "crossover_prob": 0.8,
    "error_message": null,
    "timestamp": "2025-04-10T02:15:15.475982",
    "measurement_name": "parameter_optimization_2",
    "path": "/home/ubuntu/Desktop/USVLogicSceneGeneration/src/utils/../../assets/gen_data/parameter_optimization_2/SB-MSR/pymoo_NSGA2_algorithm_actor/6vessel_0obstacle_2025-04-10T02-15-15.475982.json",
    "timeout": 180,
    "init_method": "uniform",
    "c_1": null,
    "c_2": null,
    "w": null,
    "best_fitness_index": 0.19269617225402083,
    "aggregate_strat": "actor",
    "config_group": "SB-MSR",
    "best_scene": {
        "_data": [
            [
                {
                    "id": 0,
                    "radius": 120.00000000009794,
                    "type": "OSPassengerShip",
                    "is_os": true,
                    "length": 30.000000000024485,
                    "max_speed": 20.577787999999998,
                    "beam": null,
                    "is_vessel": true
                },
                {
                    "x": 12038.006500000078,
                    "y": 12038.006499999927,
                    "speed": 2.617886088192262,
                    "heading": 1.5707963268174487
                }
            ],
            [
                {
                    "id": 1,
                    "radius": 1599.1941517784176,
                    "type": "OtherType",
                    "is_os": false,
                    "length": 399.7985379446044,
                    "max_speed": 25.722234999999998,
                    "beam": null,
                    "is_vessel": true
                },
                {
                    "x": 9880.706946256827,
                    "y": 17133.55716728411,
                    "speed": 0.36534361210897914,
                    "heading": 1.2155562451626003
                }
            ],
            [
                {
                    "id": 2,
                    "radius": 1427.802517248301,
                    "type": "OtherType",
                    "is_os": false,
                    "length": 356.95062931207525,
                    "max_speed": 25.722234999999998,
                    "beam": null,
                    "is_vessel": true
                },
                {
                    "x": 11683.719794667208,
                    "y": 18444.169091082695,
                    "speed": 0.4445550941845906,
                    "heading": 1.2175339030150605
                }
            ],
            [
                {
                    "id": 3,
                    "radius": 1504.955260692208,
                    "type": "OtherType",
                    "is_os": false,
                    "length": 376.238815173052,
                    "max_speed": 25.722234999999998,
                    "beam": null,
                    "is_vessel": true
                },
                {
                    "x": 15593.53459197301,
                    "y": 17658.253508647853,
                    "speed": 1.904633209265841,
                    "heading": 2.04740934384914
                }
            ],
            [
                {
                    "id": 4,
                    "radius": 1408.2112896324415,
                    "type": "OtherType",
                    "is_os": false,
                    "length": 352.0528224081104,
                    "max_speed": 25.722234999999998,
                    "beam": null,
                    "is_vessel": true
                },
                {
                    "x": 13862.780687377592,
                    "y": 8914.169978996755,
                    "speed": 24.894728458545753,
                    "heading": 0.22385356757432756
                }
            ],
            [
                {
                    "id": 5,
                    "radius": 1456.5574670764354,
                    "type": "OtherType",
                    "is_os": false,
                    "length": 364.13936676910885,
                    "max_speed": 25.722234999999998,
                    "beam": null,
                    "is_vessel": true
                },
                {
                    "x": 11711.279566106046,
                    "y": 17588.844488093222,
                    "speed": 0.3612779101475178,
                    "heading": 0.5363090816438137
                }
            ]
        ],
        "dcpa": null,
        "tcpa": null,
        "danger_sector": null,
        "proximity_index": null
    }
}