{
    "algorithm_desc": "pymoo_NSGA2_algorithm",
    "scenario_name": "6vessel_0obstacle",
    "random_seed": 1234,
    "vessel_number": 6,
    "obstacle_number": 0,
    "evaluation_time": 179.978672,
    "number_of_generations": 8872,
    "population_size": 5.0,
    "num_parents_mating": 2,
    "best_fitness": [
        0.001726339412195737,
        0.0,
        0.0,
        0.0011636421190185586,
        0.0004190217103063171,
        0.00014367558287086129
    ],
    "mutate_eta": 1.0,
    "mutate_prob": 0.2,
    "crossover_eta": 10.0,
    "crossover_prob": 0.5,
    "error_message": null,
    "timestamp": "2025-05-03T17:38:11.138874",
    "measurement_name": "parameter_optimization_2",
    "path": "/home/ubuntu/Desktop/USVLogicSceneGeneration/src/utils/../../assets/gen_data/parameter_optimization_2/SB-O/pymoo_NSGA2_algorithm_actor/6vessel_0obstacle_2025-05-03T17-38-11.138874.json",
    "timeout": 180,
    "init_method": "uniform",
    "c_1": null,
    "c_2": null,
    "w": null,
    "best_fitness_index": 0.001726339412195737,
    "aggregate_strat": "actor",
    "config_group": "SB-O",
    "best_scene": {
        "_data": [
            [
                {
                    "id": 0,
                    "radius": 119.99999999971072,
                    "type": "OSPassengerShip",
                    "is_os": true,
                    "length": 29.99999999992768,
                    "max_speed": 20.577787999999998,
                    "beam": null,
                    "is_vessel": true
                },
                {
                    "x": 12038.006500000087,
                    "y": 12038.006500000089,
                    "speed": 7.127109613792647,
                    "heading": 1.5707963267804035
                }
            ],
            [
                {
                    "id": 1,
                    "radius": 1367.0479055232472,
                    "type": "OtherType",
                    "is_os": false,
                    "length": 341.7619763808118,
                    "max_speed": 25.722234999999998,
                    "beam": null,
                    "is_vessel": true
                },
                {
                    "x": 3422.1369562594805,
                    "y": 8777.480896360321,
                    "speed": 20.20127004320617,
                    "heading": 0.8209799029656847
                }
            ],
            [
                {
                    "id": 2,
                    "radius": 1177.6899008706032,
                    "type": "OtherType",
                    "is_os": false,
                    "length": 294.4224752176508,
                    "max_speed": 25.722234999999998,
                    "beam": null,
                    "is_vessel": true
                },
                {
                    "x": 8900.625307414735,
                    "y": 20700.018501685012,
                    "speed": 3.865559789485863,
                    "heading": -0.510278113597899
                }
            ],
            [
                {
                    "id": 3,
                    "radius": 1339.7540353474565,
                    "type": "OtherType",
                    "is_os": false,
                    "length": 334.9385088368641,
                    "max_speed": 25.722234999999998,
                    "beam": null,
                    "is_vessel": true
                },
                {
                    "x": 3451.230199153067,
                    "y": 15709.560244007323,
                    "speed": 25.70675825197193,
                    "heading": -0.2999962343348404
                }
            ],
            [
                {
                    "id": 4,
                    "radius": 1357.5523549643983,
                    "type": "OtherType",
                    "is_os": false,
                    "length": 339.3880887410996,
                    "max_speed": 25.722234999999998,
                    "beam": null,
                    "is_vessel": true
                },
                {
                    "x": 20911.784831932215,
                    "y": 9611.194701398988,
                    "speed": 24.096035311368375,
                    "heading": 2.6800782958374394
                }
            ],
            [
                {
                    "id": 5,
                    "radius": 1462.4415605473364,
                    "type": "OtherType",
                    "is_os": false,
                    "length": 365.6103901368341,
                    "max_speed": 25.722234999999998,
                    "beam": null,
                    "is_vessel": true
                },
                {
                    "x": 20095.77455245897,
                    "y": 16708.634028398414,
                    "speed": 12.128925608458768,
                    "heading": 3.136652600509986
                }
            ]
        ],
        "dcpa": null,
        "tcpa": null,
        "danger_sector": null,
        "proximity_index": null,
        "first_level_hash": null,
        "second_level_hash": null,
        "is_relevant": null,
        "is_ambiguous": null
    }
}