{
    "algorithm_desc": "pymoo_NSGA2_algorithm",
    "scenario_name": "6vessel_0obstacle",
    "random_seed": 1234,
    "vessel_number": 6,
    "obstacle_number": 0,
    "evaluation_time": 180.214925,
    "number_of_generations": 536,
    "population_size": 100.0,
    "num_parents_mating": 2,
    "best_fitness": [
        0.02764577249121056,
        0.004692645288512188,
        0.0,
        0.0024120378811765797,
        0.017667496164023605,
        0.009807590907756548
    ],
    "mutate_eta": 15.0,
    "mutate_prob": 1.0,
    "crossover_eta": 5.0,
    "crossover_prob": 0.8,
    "error_message": null,
    "timestamp": "2025-05-03T14:24:47.354533",
    "measurement_name": "parameter_optimization_2",
    "path": "/home/ubuntu/Desktop/USVLogicSceneGeneration/src/utils/../../assets/gen_data/parameter_optimization_2/SB-O/pymoo_NSGA2_algorithm_actor/6vessel_0obstacle_2025-05-03T14-24-47.354533.json",
    "timeout": 180,
    "init_method": "uniform",
    "c_1": null,
    "c_2": null,
    "w": null,
    "best_fitness_index": 0.03111277136633974,
    "aggregate_strat": "actor",
    "config_group": "SB-O",
    "best_scene": {
        "_data": [
            [
                {
                    "id": 0,
                    "radius": 120.00000000033486,
                    "type": "OSPassengerShip",
                    "is_os": true,
                    "length": 30.000000000083716,
                    "max_speed": 20.577787999999998,
                    "beam": null,
                    "is_vessel": true
                },
                {
                    "x": 12038.006499999972,
                    "y": 12038.0064999999,
                    "speed": 19.391590607857378,
                    "heading": 1.5707963267506748
                }
            ],
            [
                {
                    "id": 1,
                    "radius": 108.58426546248782,
                    "type": "OtherType",
                    "is_os": false,
                    "length": 27.146066365621955,
                    "max_speed": 25.722234999999998,
                    "beam": null,
                    "is_vessel": true
                },
                {
                    "x": 14862.006783297225,
                    "y": 20913.359095819145,
                    "speed": 8.673185672793572,
                    "heading": -2.694159556939308
                }
            ],
            [
                {
                    "id": 2,
                    "radius": 1140.5785624078615,
                    "type": "OtherType",
                    "is_os": false,
                    "length": 285.14464060196536,
                    "max_speed": 25.722234999999998,
                    "beam": null,
                    "is_vessel": true
                },
                {
                    "x": 17125.355636065484,
                    "y": 19762.37246802114,
                    "speed": 22.000169159691715,
                    "heading": -2.7567839575949855
                }
            ],
            [
                {
                    "id": 3,
                    "radius": 1034.0543100170034,
                    "type": "OtherType",
                    "is_os": false,
                    "length": 258.51357750425086,
                    "max_speed": 25.722234999999998,
                    "beam": null,
                    "is_vessel": true
                },
                {
                    "x": 18671.334241549324,
                    "y": 18646.055228728503,
                    "speed": 17.845957168361068,
                    "heading": 2.814668360594435
                }
            ],
            [
                {
                    "id": 4,
                    "radius": 1163.9877830056482,
                    "type": "OtherType",
                    "is_os": false,
                    "length": 290.99694575141206,
                    "max_speed": 25.722234999999998,
                    "beam": null,
                    "is_vessel": true
                },
                {
                    "x": 12708.917762864747,
                    "y": 17519.956663478893,
                    "speed": 8.94285560660615,
                    "heading": 2.3218603195872998
                }
            ],
            [
                {
                    "id": 5,
                    "radius": 394.3019381305837,
                    "type": "OtherType",
                    "is_os": false,
                    "length": 98.57548453264593,
                    "max_speed": 25.722234999999998,
                    "beam": null,
                    "is_vessel": true
                },
                {
                    "x": 14879.291527390618,
                    "y": 21020.95424059185,
                    "speed": 7.304554753329587,
                    "heading": -3.0990978927660113
                }
            ]
        ],
        "dcpa": null,
        "tcpa": null,
        "danger_sector": null,
        "proximity_index": null,
        "first_level_hash": null,
        "second_level_hash": null,
        "is_relevant": null,
        "is_ambiguous": null
    }
}